Metadata-Version: 1.1
Name: django-mp-products
Version: 0.3
Summary: Django products apps
Home-page: https://github.com/pmaigutyak/mp-products
Author: Paul Maigutyak
Author-email: pmaigutyak@gmail.com
License: MIT
Download-URL: https://github.com/pmaigutyak/mp-products/archive/0.3.tar.gz
Platform: UNKNOWN
